__init__.py
kafka_manager.py
logger.py
test.py
admin/__init__.py
admin/config.py
admin/manager.py
consumer/__init__.py
consumer/config.py
consumer/decorators.py
consumer/enums.py
consumer/manager.py
decorators/singleton.py
producer/__init__.py
producer/config.py
producer/enums.py
producer/manager.py
test/__init__.py
test/handler.py
aio_kafka_manager-0.1.0.dist-info/METADATA
aio_kafka_manager-0.1.0.dist-info/WHEEL
aio_kafka_manager-0.1.0.dist-info/top_level.txt
aio_kafka_manager-0.1.0.dist-info/RECORD
