Metadata-Version: 2.4
Name: aio-kafka-manager
Version: 0.1.0
Summary: AioKafka Manager
Requires-Python: >=3.11
Requires-Dist: aiokafka>=0.12.0
Requires-Dist: pydantic-settings>=2.11.0
